Workbook

Sheet Roster
A1: Employee ID | B1: Name | C1: Department | D1: Title | E1: Level | F1: Location | G1: Start date | H1: Annual base (USD) | I1: FTE | J1: Status | K1: End date
A2: E1001 | B2: Maya Novak | C2: RND | D2: Senior Software Engineer | E2: L5 | F2: Lisbon, PT | G2: 46178 | H2: 293000 | I2: 1 | J2: Active
A3: E1002 | B3: Nora Varga | C3: RND | D3: Software Engineer | E3: L6 | F3: Lisbon, PT | G3: 44645 | H3: 287000 | I3: 1 | J3: Active
A4: E1003 | B4: Zoe Mensah | C4: RND | D4: Software Engineer | E4: L4 | F4: Remote US | G4: 46002 | H4: 220000 | I4: 1 | J4: Active
A5: E1004 | B5: Isla Novak | C5: RND | D5: Engineering Manager | E5: L1 | F5: Berlin, DE | G5: 45809 | H5: 116000 | I5: 0.8 | J5: Active
A6: E1005 | B6: Noah Novak | C6: RND | D6: Data Engineer | E6: L1 | F6: Denver, CO | G6: 43765 | H6: 96000 | I6: 1 | J6: Active
A7: E1006 | B7: Ivan Silva | C7: RND | D7: Senior Software Engineer | E7: L6 | F7: Remote US | G7: 44675 | H7: 325000 | I7: 1 | J7: Terminated | K7: 46199
A8: E1007 | B8: Leila Ibrahim | C8: RND | D8: Data Engineer | E8: L5 | F8: Austin, TX | G8: 44775 | H8: 222000 | I8: 1 | J8: Active
A9: E1008 | B9: Kai Moreau | C9: RND | D9: Staff Engineer | E9: L4 | F9: Austin, TX | G9: 43634 | H9: 222000 | I9: 1 | J9: Active
A10: E1009 | B10: Nora Lindqvist | C10: RND | D10: Senior Software Engineer | E10: L6 | F10: Remote US | G10: 45252 | H10: 385000 | I10: 1 | J10: Active
A11: E1010 | B11: Isla Duarte | C11: RND | D11: Senior Software Engineer | E11: L3 | F11: Remote US | G11: 44513 | H11: 200000 | I11: 1 | J11: Active
A12: E1011 | B12: Arjun Haddad | C12: RND | D12: Software Engineer | E12: L3 | F12: Denver, CO | G12: 45760 | H12: 161000 | I12: 1 | J12: Active
A13: E1012 | B13: Rosa Haddad | C13: RND | D13: Engineering Manager | E13: L3 | F13: Remote US | G13: 44358 | H13: 194000 | I13: 1 | J13: Active
A14: E1013 | B14: Sara Haddad | C14: RND | D14: Senior Software Engineer | E14: L3 | F14: Austin, TX | G14: 43638 | H14: 186000 | I14: 1 | J14: Active
A15: E1014 | B15: Arjun Okafor | C15: RND | D15: Staff Engineer | E15: L2 | F15: Berlin, DE | G15: 45048 | H15: 138000 | I15: 1 | J15: Active
A16: E1015 | B16: Zoe Brennan | C16: RND | D16: Software Engineer | E16: L2 | F16: Remote US | G16: 44569 | H16: 125000 | I16: 1 | J16: Active
A17: E1016 | B17: Chloe Tanaka | C17: RND | D17: Software Engineer | E17: L4 | F17: Austin, TX | G17: 45976 | H17: 204000 | I17: 1 | J17: Active
A18: E1017 | B18: Isla Brennan | C18: RND | D18: Senior Software Engineer | E18: L2 | F18: Berlin, DE | G18: 45775 | H18: 149000 | I18: 1 | J18: Active
A19: E1018 | B19: Noah Fischer | C19: RND | D19: Senior Software Engineer | E19: L2 | F19: Austin, TX | G19: 44466 | H19: 125000 | I19: 1 | J19: Active
... A33: E1032 | B33: Felix Ibrahim | C33: RND | D33: Data Engineer | E33: L3 | F33: Berlin, DE | G33: 46081 | H33: 155000 | I33: 1 | J33: Active
A34: E1033 | B34: Kai Duarte | C34: RND | D34: Data Engineer | E34: L3 | F34: Austin, TX | G34: 45418 | H34: 178000 | I34: 1 | J34: Terminated | K34: 46065
A35: E1034 | B35: Chloe Jensen | C35: RND | D35: Staff Engineer | E35: L4 | F35: Lisbon, PT | G35: 45368 | H35: 187000 | I35: 1 | J35: Active
A36: E1035 | B36: Mateo Silva | C36: RND | D36: Data Engineer | E36: L5 | F36: Austin, TX | G36: 45531 | H36: 258000 | I36: 1 | J36: Active
A37: E1036 | B37: Chloe Kowalski | C37: RND | D37: Software Engineer | E37: L3 | F37: Austin, TX | G37: 45590 | H37: 148000 | I37: 1 | J37: Active
A38: E1037 | B38: Lena Varga | C38: RND | D38: Data Engineer | E38: L3 | F38: Denver, CO | G38: 44098 | H38: 163000 | I38: 1 | J38: Active
A39: E1038 | B39: Maya Castillo | C39: RND | D39: Data Engineer | E39: L5 | F39: Denver, CO | G39: 44832 | H39: 236000 | I39: 1 | J39: Active
A40: E1039 | B40: Maya Achebe | C40: RND | D40: Senior Software Engineer | E40: L3 | F40: Denver, CO | G40: 46047 | H40: 192000 | I40: 1 | J40: Active
A41: E1040 | B41: Chloe Haddad | C41: RND | D41: Software Engineer | E41: L5 | F41: Lisbon, PT | G41: 44845 | H41: 266000 | I41: 1 | J41: Active
A42: E1041 | B42: Sara Castillo | C42: RND | D42: Data Engineer | E42: L2 | F42: Austin, TX | G42: 45936 | H42: 152000 | I42: 1 | J42: Active
A43: E1042 | B43: Elif Tanaka | C43: RND | D43: Staff Engineer | E43: L4 | F43: Austin, TX | G43: 44505 | H43: 232000 | I43: 1 | J43: Active
A44: E1043 | B44: Kai Nakamura | C44: RND | D44: Software Engineer | E44: L4 | F44: Berlin, DE | G44: 45949 | H44: 246000 | I44: 1 | J44: Active
A45: E1044 | B45: Mia Nakamura | C45: RND | D45: Senior Software Engineer | E45: L3 | F45: Austin, TX | G45: 46088 | H45: 198000 | I45: 1 | J45: Active
A46: E1045 | B46: Ines Varga | C46: RND | D46: Data Engineer | E46: L4 | F46: Denver, CO | G46: 44982 | H46: 179000 | I46: 1 | J46: Active
... A49: E1048 | B49: Isla Petrova | C49: SAL | D49: Sales Development Rep | E49: L4 | F49: Remote US | G49: 43647 | H49: 192000 | I49: 1 | J49: Active
A50: E1049 | B50: Nora Kowalski | C50: SAL | D50: Regional Sales Manager | E50: L2 | F50: Berlin, DE | G50: 45650 | H50: 137000 | I50: 1 | J50: Terminated | K50: 46266
A51: E1050 | B51: Mia Haddad | C51: SAL | D51: Regional Sales Manager | E51: L3 | F51: Austin, TX | G51: 45528 | H51: 149000 | I51: 1 | J51: Active
A52: E1051 | B52: Lucas Kowalski | C52: SAL | D52: Account Executive | E52: L2 | F52: Berlin, DE | G52: 45635 | H52: 123000 | I52: 1 | J52: Active
A53: E1052 | B53: Ravi Jensen | C53: SAL | D53: Sales Development Rep | E53: L6 | F53: Berlin, DE | G53: 44615 | H53: 400000 | I53: 0.8 | J53: Active
A54: E1053 | B54: Kai Castillo | C54: SAL | D54: Regional Sales Manager | E54: L5 | F54: Austin, TX | G54: 44092 | H54: 227000 | I54: 1 | J54: Active
A55: E1054 | B55: Liam Petrova | C55: SAL | D55: Account Executive | E55: L1 | F55: Austin, TX | G55: 45466 | H55: 112000 | I55: 1 | J55: Terminated | K55: 46197
A56: E1055 | B56: Ava Tanaka | C56: SAL | D56: Regional Sales Manager | E56: L4 | F56: Remote US | G56: 46050 | H56: 222000 | I56: 1 | J56: Active
A57: E1056 | B57: Jonas Ibrahim | C57: SAL | D57: Account Executive | E57: L2 | F57: Denver, CO | G57: 45316 | H57: 130000 | I57: 1 | J57: Active
A58: E1057 | B58: Ines Duarte | C58: SAL | D58: Sales Engineer | E58: L4 | F58: Denver, CO | G58: 45720 | H58: 233000 | I58: 1 | J58: Active
A59: E1058 | B59: Rosa Lindqvist | C59: SAL | D59: Regional Sales Manager | E59: L6 | F59: Berlin, DE | G59: 45940 | H59: 368000 | I59: 0.8 | J59: Active
A60: E1059 | B60: Omar Castillo | C60: SAL | D60: Sales Engineer | E60: L3 | F60: Berlin, DE | G60: 45759 | H60: 175000 | I60: 1 | J60: Active
A61: E1060 | B61: Noah Haddad | C61: SAL | D61: Sales Engineer | E61: L1 | F61: Austin, TX | G61: 45418 | H61: 118000 | I61: 1 | J61: Terminated | K61: 46151
A62: E1061 | B62: Mia Silva | C62: SAL | D62: Regional Sales Manager | E62: L2 | F62: Lisbon, PT | G62: 43528 | H62: 141000 | I62: 1 | J62: Active
A63: E1062 | B63: Arjun Nakamura | C63: SAL | D63: Regional Sales Manager | E63: L5 | F63: Lisbon, PT | G63: 45974 | H63: 272000 | I63: 1 | J63: Active
A64: E1063 | B64: Noah Petrova | C64: SAL | D64: Regional Sales Manager | E64: L2 | F64: Austin, TX | G64: 46104 | H64: 148000 | I64: 1 | J64: Active
A65: E1064 | B65: Ethan Petrova | C65: SAL | D65: Sales Development Rep | E65: L2 | F65: Austin, TX | G65: 46083 | H65: 111000 | I65: 1 | J65: Active
A66: E1065 | B66: Diego Jensen | C66: SAL | D66: Sales Development Rep | E66: L4 | F66: Berlin, DE | G66: 45938 | H66: 177000 | I66: 1 | J66: Active
A67: E1066 | B67: Maya Okafor | C67: SAL | D67: Regional Sales Manager | E67: L3 | F67: Remote US | G67: 45115 | H67: 168000 | I67: 0.8 | J67: Active
A68: E1067 | B68: Tariq Varga | C68: SAL | D68: Sales Development Rep | E68: L1 | F68: Berlin, DE | G68: 44171 | H68: 120000 | I68: 1 | J68: Active
A69: E1068 | B69: Nora Rahman | C69: SAL | D69: Regional Sales Manager | E69: L2 | F69: Austin, TX | G69: 44427 | H69: 115000 | I69: 1 | J69: Active
A70: E1069 | B70: Tariq Brennan | C70: SAL | D70: Account Executive | E70: L2 | F70: Austin, TX | G70: 44759 | H70: 121000 | I70: 1 | J70: Terminated | K70: 46044
A71: E1070 | B71: Ivan Varga | C71: SAL | D71: Sales Engineer | E71: L1 | F71: Austin, TX | G71: 43807 | H71: 111000 | I71: 1 | J71: Active
A72: E1071 | B72: Isla Moreau | C72: CS | D72: Support Engineer | E72: L4 | F72: Lisbon, PT | G72: 45539 | H72: 248000 | I72: 1 | J72: Active
A73: E1072 | B73: Chloe Nakamura | C73: CS | D73: Customer Success Manager | E73: L1 | F73: Austin, TX | G73: 45097 | H73: 108000 | I73: 1 | J73: Active
A74: E1073 | B74: Ivan Lindqvist | C74: CS | D74: CS Team Lead | E74: L5 | F74: Austin, TX | G74: 44219 | H74: 283000 | I74: 0.8 | J74: Terminated | K74: 46273
A75: E1074 | B75: Leila Brennan | C75: CS | D75: Customer Success Manager | E75: L2 | F75: Austin, TX | G75: 43561 | H75: 146000 | I75: 1 | J75: Active
A76: E1075 | B76: Theo Varga | C76: CS | D76: Customer Success Manager | E76: L3 | F76: Austin, TX | G76: 45539 | H76: 187000 | I76: 1 | J76: Active
A77: E1076 | B77: Ava Brennan | C77: CS | D77: Onboarding Specialist | E77: L4 | F77: Remote US | G77: 43506 | H77: 241000 | I77: 1 | J77: Active
A78: E1077 | B78: Jonas Varga | C78: CS | D78: Onboarding Specialist | E78: L3 | F78: Remote US | G78: 43807 | H78: 159000 | I78: 1 | J78: Active
A79: E1078 | B79: Ines Silva | C79: CS | D79: CS Team Lead | E79: L3 | F79: Austin, TX | G79: 45146 | H79: 183000 | I79: 1 | J79: Terminated | K79: 46069
A80: E1079 | B80: Kai Tanaka | C80: CS | D80: Onboarding Specialist | E80: L3 | F80: Austin, TX | G80: 44013 | H80: 169000 | I80: 1 | J80: Active
A81: E1080 | B81: Leila Duarte | C81: CS | D81: CS Team Lead | E81: L3 | F81: Lisbon, PT | G81: 43615 | H81: 182000 | I81: 1 | J81: Active
A82: E1081 | B82: Tariq Achebe | C82: CS | D82: Onboarding Specialist | E82: L2 | F82: Denver, CO | G82: 46130 | H82: 110000 | I82: 1 | J82: Active
A83: E1082 | B83: Sara Silva | C83: CS | D83: Support Engineer | E83: L2 | F83: Austin, TX | G83: 43790 | H83: 145000 | I83: 0.8 | J83: Active
A84: E1083 | B84: Hana Brennan | C84: CS | D84: Customer Success Manager | E84: L1 | F84: Berlin, DE | G84: 43962 | H84: 119000 | I84: 1 | J84: Active
A85: E1084 | B85: Isla Nakamura | C85: CS | D85: Customer Success Manager | E85: L2 | F85: Remote US | G85: 45393 | H85: 125000 | I85: 1 | J85: Active
A86: E1085 | B86: Mia Tanaka | C86: CS | D86: Onboarding Specialist | E86: L2 | F86: Remote US | G86: 46158 | H86: 126000 | I86: 1 | J86: Active
A87: E1086 | B87: Elif Novak | C87: CS | D87: Onboarding Specialist | E87: L3 | F87: Berlin, DE | G87: 44034 | H87: 154000 | I87: 1 | J87: Active
A88: E1087 | B88: Leila Fischer | C88: CS | D88: Onboarding Specialist | E88: L2 | F88: Remote US | G88: 43879 | H88: 158000 | I88: 1 | J88: Active
A89: E1088 | B89: Ines Okafor | C89: CS | D89: CS Team Lead | E89: L2 | F89: Berlin, DE | G89: 44604 | H89: 156000 | I89: 1 | J89: Active
A90: E1089 | B90: Sara Ibrahim | C90: MKT | D90: Demand Gen Manager | E90: L1 | F90: Austin, TX | G90: 46070 | H90: 124000 | I90: 1 | J90: Active
A91: E1090 | B91: Omar Varga | C91: MKT | D91: Marketing Manager | E91: L2 | F91: Berlin, DE | G91: 45428 | H91: 132000 | I91: 1 | J91: Active
... A109: E1108 | B109: Ravi Tanaka | C109: PRD | D109: Senior Product Manager | E109: L1 | F109: Lisbon, PT | G109: 45243 | H109: 107000 | I109: 1 | J109: Active
A110: E1109 | B110: Isla Silva | C110: GA | D110: Accountant | E110: L4 | F110: Austin, TX | G110: 43513 | H110: 180000 | I110: 1 | J110: Terminated | K110: 46087
A111: E1110 | B111: Ethan Kowalski | C111: GA | D111: Recruiter | E111: L2 | F111: Remote US | G111: 44104 | H111: 154000 | I111: 1 | J111: Active
A112: E1111 | B112: Lena Tanaka | C112: GA | D112: IT Administrator | E112: L1 | F112: Berlin, DE | G112: 43744 | H112: 129000 | I112: 1 | J112: Active
A113: E1112 | B113: Yara Okafor | C113: GA | D113: Legal Counsel | E113: L5 | F113: Berlin, DE | G113: 44620 | H113: 260000 | I113: 1 | J113: Active
A114: E1113 | B114: Mateo Okafor | C114: GA | D114: Accountant | E114: L3 | F114: Denver, CO | G114: 46137 | H114: 162000 | I114: 1 | J114: Active
A115: E1114 | B115: Leila Petrova | C115: GA | D115: Legal Counsel | E115: L2 | F115: Austin, TX | G115: 44109 | H115: 159000 | I115: 1 | J115: Active
A116: E1115 | B116: Ravi Haddad | C116: GA | D116: FP&A Analyst | E116: L4 | F116: Austin, TX | G116: 43989 | H116: 245000 | I116: 1 | J116: Terminated | K116: 46057
A117: E1116 | B117: Elif Jensen | C117: GA | D117: IT Administrator | E117: L1 | F117: Berlin, DE | G117: 46196 | H117: 91000 | I117: 1 | J117: Active
A118: E1117 | B118: Isla Fischer | C118: GA | D118: IT Administrator | E118: L4 | F118: Berlin, DE | G118: 45504 | H118: 218000 | I118: 1 | J118: Active
A119: E1118 | B119: Chloe Ibrahim | C119: GA | D119: Legal Counsel | E119: L2 | F119: Austin, TX | G119: 44076 | H119: 133000 | I119: 1 | J119: Active
A120: E1119 | B120: Arjun Rahman | C120: GA | D120: Recruiter | E120: L3 | F120: Remote US | G120: 44741 | H120: 191000 | I120: 1 | J120: Active
A121: E1120 | B121: Maya Fischer | C121: GA | D121: Recruiter | E121: L1 | F121: Lisbon, PT | G121: 45682 | H121: 119000 | I121: 1 | J121: Active

Sheet Comp Bands
A1: Level | B1: Min | C1: Mid | D1: Max | E1: Bonus target %
A2: L1 | B2: 90000 | C2: 110000 | D2: 130000 | E2: 0.05
A3: L2 | B3: 110000 | C3: 135000 | D3: 160000 | E3: 0.08
A4: L3 | B4: 140000 | C4: 170000 | D4: 200000 | E4: 0.1
A5: L4 | B5: 175000 | C5: 210000 | D5: 250000 | E5: 0.12
A6: L5 | B6: 220000 | C6: 265000 | D6: 320000 | E6: 0.15
A7: L6 | B7: 280000 | C7: 340000 | D7: 420000 | E7: 0.2
A9: Bands effective 2026-01-01 (Radford Q4 FY25 refresh).

Sheet Hiring Plan
A1: Req ID | B1: Department | C1: Title | D1: Level | E1: Planned start | F1: Status | G1: Offer salary (USD) | H1: Hiring manager
A2: REQ-0401 | B2: SAL | C2: Account Executive | D2: L2 | E2: 46204 | F2: Cancelled | G2: 111000 | H2: Priya Natarajan
A3: REQ-0402 | B3: SAL | C3: Regional Sales Manager | D3: L3 | E3: 46174 | F3: Offer out | G3: 168000 | H3: Priya Natarajan
A4: REQ-0403 | B4: SAL | C4: Account Executive | D4: L4 | E4: 46082 | F4: Hired | G4: 222000 | H4: Priya Natarajan
A5: REQ-0404 | B5: SAL | C5: Sales Development Rep | D5: L2 | E5: 46327 | F5: Open | G5: 145000 | H5: Priya Natarajan
A6: REQ-0405 | B6: SAL | C6: Regional Sales Manager | D6: L4 | E6: 46266 | F6: Open | G6: 195000 | H6: Priya Natarajan
A7: REQ-0406 | B7: MKT | C7: Content Lead | D7: L2 | E7: 46204 | F7: Hired | G7: 155000 | H7: Luis Ortega
A8: REQ-0407 | B8: MKT | C8: Marketing Manager | D8: L3 | E8: 46174 | F8: Hired | G8: 189000 | H8: Luis Ortega
A9: REQ-0408 | B9: CS | C9: CS Team Lead | D9: L4 | E9: 46327 | F9: Open | G9: 241000 | H9: Hannah Weiss
A10: REQ-0409 | B10: CS | C10: Onboarding Specialist | D10: L4 | E10: 46235 | F10: Hired | G10: 185000 | H10: Hannah Weiss
A11: REQ-0410 | B11: CS | C11: Onboarding Specialist | D11: L3 | E11: 46054 | F11: Open | G11: 190000 | H11: Hannah Weiss
A12: REQ-0412 | B12: RND | C12: Senior Software Engineer | D12: L3 | E12: 46204 | F12: Slipped to Q4 | G12: 146000 | H12: Wei Zhang
A13: REQ-0413 | B13: RND | C13: Data Engineer | D13: L2 | E13: 46235 | F13: Slipped to Q4 | G13: 139000 | H13: Wei Zhang
... A31: REQ-0430 | B31: GA | C31: People Ops Partner | D31: L3 | E31: 46296 | F31: Open | G31: 194000 | H31: Tom Hadley

Sheet HC Summary
A1: Ardent Labs, Inc. FY2026 Headcount and loaded compensation
A2: Benefits load (Jan to Sep) | B2: 0.22
A3: Benefits load (Q4 forecast) | B3: 0.25
A5: Month | B5: Beginning HC | C5: Hires | D5: Attrition | E5: Ending HC | F5: Monthly base comp | G5: Loaded comp | H5: Budget loaded comp | I5: Variance
A6: 46023 | B6: 104 | C6: =COUNTIFS('Hiring Plan'!$E:$E,">="&A6,'Hiring Plan'!$E:$E,"<="&EOMONTH(A6,0),'Hiring Plan'!$F:$F,"Hired") -> 0 | D6: 1 | E6: =B6+C6-D6 -> 103 | F6: =SUMIFS(Roster!$H:$H,Roster!$G:$G,"<="&EOMONTH(A6,0),Roster!$J:$J,"Active")/12 -> 1524250 | G6: =F6*(1+$B$2) -> 1859585 | H6: 2221209 | I6: =G6-H6 -> -361624
A7: 46054 | B7: =E6 -> 103 | C7: =COUNTIFS('Hiring Plan'!$E:$E,">="&A7,'Hiring Plan'!$E:$E,"<="&EOMONTH(A7,0),'Hiring Plan'!$F:$F,"Hired") -> 0 | D7: 2 | E7: =B7+C7-D7 -> 101 | F7: =SUMIFS(Roster!$H:$H,Roster!$G:$G,"<="&EOMONTH(A7,0),Roster!$J:$J,"Active")/12 -> 1547500 | G7: =F7*(1+$B$2) -> 1887950 | H7: 2245696 | I7: =G7-H7 -> -357746
A8: 46082 | B8: =E7 -> 101 | C8: =COUNTIFS('Hiring Plan'!$E:$E,">="&A8,'Hiring Plan'!$E:$E,"<="&EOMONTH(A8,0),'Hiring Plan'!$F:$F,"Hired") -> 2 | D8: 1 | E8: =B8+C8-D8 -> 102 | F8: =SUMIFS(Roster!$H:$H,Roster!$G:$G,"<="&EOMONTH(A8,0),Roster!$J:$J,"Active")/12 -> 1585583.3 | G8: =F8*(1+$B$2) -> 1934411.7 | H8: 2231923 | I8: =G8-H8 -> -297511.33
A9: 46113 | B9: =E8 -> 102 | C9: =COUNTIFS('Hiring Plan'!$E:$E,">="&A9,'Hiring Plan'!$E:$E,"<="&EOMONTH(A9,0),'Hiring Plan'!$F:$F,"Hired") -> 1 | D9: 0 | E9: =B9+C9-D9 -> 103 | F9: =SUMIFS(Roster!$H:$H,Roster!$G:$G,"<="&EOMONTH(A9,0),Roster!$J:$J,"Active")/12 -> 1608250 | G9: =F9*(1+$B$2) -> 1962065 | H9: 2271520 | I9: =G9-H9 -> -309455
A10: 46143 | B10: =E9 -> 103 | C10: =COUNTIFS('Hiring Plan'!$E:$E,">="&A10,'Hiring Plan'!$E:$E,"<="&EOMONTH(A10,0),'Hiring Plan'!$F:$F,"Hired") -> 3 | D10: 2 | E10: =B10+C10-D10 -> 104 | F10: =SUMIFS(Roster!$H:$H,Roster!$G:$G,"<="&EOMONTH(A10,0),Roster!$J:$J,"Active")/12 -> 1632833.3 | G10: =F10*(1+$B$2) -> 1992056.7 | H10: 2336048 | I10: =G10-H10 -> -343991.33
A11: 46174 | B11: =E10 -> 104 | C11: =COUNTIFS('Hiring Plan'!$E:$E,">="&A11,'Hiring Plan'!$E:$E,"<="&EOMONTH(A11,0),'Hiring Plan'!$F:$F,"Hired") -> 1 | D11: 1 | E11: =B11+C11-D11 -> 104 | F11: =SUMIFS(Roster!$H:$H,Roster!$G:$G,"<="&EOMONTH(A11,0),Roster!$J:$J,"Active")/12 -> 1710583.3 | G11: =F11*(1+$B$2) -> 2086911.7 | H11: 2285103 | I11: =G11-H11 -> -198191.33
A12: 46204 | B12: =E11 -> 104 | C12: =COUNTIFS('Hiring Plan'!$E:$E,">="&A12,'Hiring Plan'!$E:$E,"<="&EOMONTH(A12,0),'Hiring Plan'!$F:$F,"Hired") -> 1 | D12: 3 | E12: =B12+C12-D12 -> 102 | F12: =SUMIFS(Roster!$H:$H,Roster!$G:$G,"<="&EOMONTH(A12,0),Roster!$J:$J,"Active")/12 -> 1710583.3 | G12: =F12*(1+$B$2) -> 2086911.7 | H12: 2358240 | I12: =G12-H12 -> -271328.33
A13: 46235 | B13: =E12 -> 102 | C13: =COUNTIFS('Hiring Plan'!$E:$E,">="&A13,'Hiring Plan'!$E:$E,"<="&EOMONTH(A13,0),'Hiring Plan'!$F:$F,"Hired") -> 2 | D13: 1 | E13: =B13+C13-D13 -> 103 | F13: =SUMIFS(Roster!$H:$H,Roster!$G:$G,"<="&EOMONTH(A13,0),Roster!$J:$J,"Active")/12 -> 1710583.3 | G13: =F13*(1+$B$2) -> 2086911.7 | H13: 2403183 | I13: =G13-H13 -> -316271.33
A14: 46266 | B14: =E13 -> 103 | C14: =COUNTIFS('Hiring Plan'!$E:$E,">="&A14,'Hiring Plan'!$E:$E,"<="&EOMONTH(A14,0),'Hiring Plan'!$F:$F,"Hired") -> 0 | D14: 2 | E14: =B14+C14-D14 -> 101 | F14: =SUMIFS(Roster!$H:$H,Roster!$G:$G,"<="&EOMONTH(A14,0),Roster!$J:$J,"Active")/12 -> 1710583.3 | G14: =F14*(1+$B$2) -> 2086911.7 | H14: 2394511 | I14: =G14-H14 -> -307599.33
A15: 46296 | B15: =E14 -> 101 | C15: =COUNTIFS('Hiring Plan'!$E:$E,">="&A15,'Hiring Plan'!$E:$E,"<="&EOMONTH(A15,0),'Hiring Plan'!$F:$F,"Hired") -> 0 | D15: 1 | E15: =B15+C15-D15 -> 100 | F15: =SUMIFS(Roster!$H:$H,Roster!$G:$G,"<="&EOMONTH(A15,0),Roster!$J:$J,"Active")/12 -> 1710583.3 | G15: =F15*(1+$B$3) -> 2138229.2 | H15: 2433961 | I15: =G15-H15 -> -295731.83
A16: 46327 | B16: =E15 -> 100 | C16: =COUNTIFS('Hiring Plan'!$E:$E,">="&A16,'Hiring Plan'!$E:$E,"<="&EOMONTH(A16,0),'Hiring Plan'!$F:$F,"Hired") -> 0 | D16: 1 | E16: =B16+C16-D16 -> 99 | F16: =SUMIFS(Roster!$H:$H,Roster!$G:$G,"<="&EOMONTH(A16,0),Roster!$J:$J,"Active")/12 -> 1710583.3 | G16: =F16*(1+$B$3) -> 2138229.2 | H16: 2463234 | I16: =G16-H16 -> -325004.83
A17: 46357 | B17: =E16 -> 99 | C17: =COUNTIFS('Hiring Plan'!$E:$E,">="&A17,'Hiring Plan'!$E:$E,"<="&EOMONTH(A17,0),'Hiring Plan'!$F:$F,"Hired") -> 0 | D17: 1 | E17: =B17+C17-D17 -> 98 | F17: =SUMIFS(Roster!$H:$H,Roster!$G:$G,"<="&EOMONTH(A17,0),Roster!$J:$J,"Active")/12 -> 1710583.3 | G17: =F17*(1+$B$3) -> 2138229.2 | H17: 2467991 | I17: =G17-H17 -> -329761.83
A18: Total | C18: =SUM(C6:C17) -> 10 | D18: =SUM(D6:D17) -> 16 | F18: =SUM(F6:F17) -> 19872500 | G18: =SUM(G6:G17) -> 24398402 | H18: =SUM(H6:H17) -> 28112619 | I18: =SUM(I6:I17) -> -3714216.5
A20: Notes
A21: Beginning HC chains from the prior month's Ending HC.
A22: Hires counts Hiring Plan rows with status Hired by planned start month; actual start dates are in Workday, not here.
A23: Monthly base comp sums active roster base salaries with a start date on or before month end, divided by 12.
A24: Loaded comp applies the benefits load in B2 for Jan to Sep and B3 for Q4.
